{
  "/admin/courses/page": "app/admin/courses/page.js",
  "/admin/login/page": "app/admin/login/page.js",
  "/admin/units/page": "app/admin/units/page.js",
  "/api/courses/route": "app/api/courses/route.js",
  "/courses/[courseSlug]/[semesterSlug]/[subjectSlug]/[unitSlug]/page": "app/courses/[courseSlug]/[semesterSlug]/[subjectSlug]/[unitSlug]/page.js",
  "/courses/[courseSlug]/[semesterSlug]/[subjectSlug]/page": "app/courses/[courseSlug]/[semesterSlug]/[subjectSlug]/page.js",
  "/courses/[courseSlug]/[semesterSlug]/page": "app/courses/[courseSlug]/[semesterSlug]/page.js",
  "/courses/[courseSlug]/page": "app/courses/[courseSlug]/page.js",
  "/courses/page": "app/courses/page.js",
  "/favicon.ico/route": "app/favicon.ico/route.js",
  "/page": "app/page.js"
}